odoo/addons/ssi_status_check_mixin/README.rst
odoo/addons/ssi_status_check_mixin/__init__.py
odoo/addons/ssi_status_check_mixin/__manifest__.py
odoo/addons/ssi_status_check_mixin/menu.xml
odoo/addons/ssi_status_check_mixin/i18n/ssi_status_check_mixin.pot
odoo/addons/ssi_status_check_mixin/models/__init__.py
odoo/addons/ssi_status_check_mixin/models/mixin_status_check.py
odoo/addons/ssi_status_check_mixin/models/status_check.py
odoo/addons/ssi_status_check_mixin/models/status_check_item.py
odoo/addons/ssi_status_check_mixin/models/status_check_template.py
odoo/addons/ssi_status_check_mixin/models/status_check_template_detail.py
odoo/addons/ssi_status_check_mixin/security/ir.model.access.csv
odoo/addons/ssi_status_check_mixin/static/description/icon.png
odoo/addons/ssi_status_check_mixin/templates/status_check_templates.xml
odoo/addons/ssi_status_check_mixin/views/status_check_item_views.xml
odoo/addons/ssi_status_check_mixin/views/status_check_template_detail_views.xml
odoo/addons/ssi_status_check_mixin/views/status_check_template_views.xml
odoo/addons/ssi_status_check_mixin/views/status_check_views.xml
odoo14_addon_ssi_status_check_mixin-14.0.2.4.3.dist-info/METADATA
odoo14_addon_ssi_status_check_mixin-14.0.2.4.3.dist-info/WHEEL
odoo14_addon_ssi_status_check_mixin-14.0.2.4.3.dist-info/top_level.txt
odoo14_addon_ssi_status_check_mixin-14.0.2.4.3.dist-info/RECORD
